local_reranker/__init__.py
local_reranker/api.py
local_reranker/models.py
local_reranker/reranker.py
local_reranker/utils.py
local_reranker-0.1.1.dist-info/licenses/LICENSE
local_reranker-0.1.1.dist-info/METADATA
local_reranker-0.1.1.dist-info/WHEEL
local_reranker-0.1.1.dist-info/entry_points.txt
local_reranker-0.1.1.dist-info/top_level.txt
local_reranker-0.1.1.dist-info/RECORD
