Metadata-Version: 2.4
Name: local-reranker
Version: 0.1.1
Summary: A lightweight, local reranker API implementation compatible with Jina.
Author-email: Olaf Geibig <olaf@pobox.com>
Project-URL: Homepage, https://github.com/olafgeibig/local-reranker
Project-URL: Bug Tracker, https://github.com/olafgeibig/local-reranker/issues
Keywords: reranker,local,jina,api,rag,nlp,machine learning
Classifier: Programming Language :: Python :: 3
Classifier: License :: OSI Approved :: MIT License
Classifier: Operating System :: OS Independent
Classifier: Topic :: Scientific/Engineering :: Artificial Intelligence
Classifier: Topic :: Software Development :: Libraries :: Python Modules
Classifier: Intended Audience :: Developers
Requires-Python: >=3.9
License-File: LICENSE
Requires-Dist: fastapi<0.110.0,>=0.109.0
Requires-Dist: uvicorn[standard]<0.30.0,>=0.29.0
Requires-Dist: pydantic<3.0,>=2.0
Requires-Dist: sentence-transformers<4.1.0,>=4.0.2
Requires-Dist: torch<3.0.0,>=2.0.0
Requires-Dist: transformers<5.0.0,>=4.51.3
Requires-Dist: tokenizers<0.22.0,>=0.21.1
Requires-Dist: accelerate<0.29.0,>=0.28.0
Requires-Dist: einops<0.9.0,>=0.8.0
Provides-Extra: dev
Requires-Dist: pytest<9.0.0,>=8.0.0; extra == "dev"
Requires-Dist: pytest-mock<4.0.0,>=3.0.0; extra == "dev"
Requires-Dist: httpx<0.28.0,>=0.27.0; extra == "dev"
Requires-Dist: uvicorn[standard]<0.30.0,>=0.29.0; extra == "dev"
Requires-Dist: ruff<0.5.0,>=0.4.0; extra == "dev"
Dynamic: license-file
